netbox_snmp/__init__.py
netbox_snmp/choices.py
netbox_snmp/filtersets.py
netbox_snmp/forms.py
netbox_snmp/models.py
netbox_snmp/navigation.py
netbox_snmp/tables.py
netbox_snmp/urls.py
netbox_snmp/views.py
netbox_snmp/api/__init__.py
netbox_snmp/api/serializers.py
netbox_snmp/api/urls.py
netbox_snmp/api/views.py
netbox_snmp/migrations/0001_initial.py
netbox_snmp/migrations/0002_userprofiles.py
netbox_snmp/migrations/0003_viewtrees.py
netbox_snmp/migrations/0004_rename_viewtrees_mibtrees.py
netbox_snmp/migrations/0005_trapprofiles_user_profile.py
netbox_snmp/migrations/0006_notifyprofiles.py
netbox_snmp/migrations/0007_rename__type_notifyprofiles_noti_type.py
netbox_snmp/migrations/0008_rename_noti_type_notifyprofiles_notification_type.py
netbox_snmp/migrations/0009_alter_mibtrees_oid.py
netbox_snmp/migrations/__init__.py
netbox_snmp/templates/netbox_snmp/mibtrees.html
netbox_snmp/templates/netbox_snmp/notifyprofiles.html
netbox_snmp/templates/netbox_snmp/trapprofiles.html
netbox_snmp/templates/netbox_snmp/userprofiles.html
netbox_snmp-0.4.1.dist-info/METADATA
netbox_snmp-0.4.1.dist-info/WHEEL
netbox_snmp-0.4.1.dist-info/top_level.txt
netbox_snmp-0.4.1.dist-info/RECORD
