Metadata-Version: 2.4
Name: netbox-snmp
Version: 0.4.1
Summary: NetBox SNMP is a NetBox plugin for managing SNMP data.
Author: AGE Solutions
Author-email: Michael Terrero <michael.terrero@age.solutions>
Keywords: netbox,netbox-plugin,snmp
Classifier: Development Status :: 5 - Production/Stable
Classifier: Programming Language :: Python :: 3 :: Only
Classifier: Programming Language :: Python :: 3.12
Classifier: Programming Language :: Python :: 3.13
Classifier: Programming Language :: Python :: 3.14
Requires-Python: >=3.12
Dynamic: author
